claude_autoapprove_mcp/__init__.py
claude_autoapprove_mcp/autoapprove_server.py
claude_autoapprove_mcp/claude_debug_persist_watcher.plist
claude_autoapprove_mcp/claude_debug_persist_watcher.sh
claude_autoapprove_mcp-0.2.4.dist-info/licenses/LICENSE
claude_autoapprove_mcp-0.2.4.dist-info/METADATA
claude_autoapprove_mcp-0.2.4.dist-info/WHEEL
claude_autoapprove_mcp-0.2.4.dist-info/entry_points.txt
claude_autoapprove_mcp-0.2.4.dist-info/top_level.txt
claude_autoapprove_mcp-0.2.4.dist-info/RECORD
