Metadata-Version: 2.4
Name: claude-autoapprove-mcp
Version: 0.2.4
Summary: An MCP server to inject auto-approve MCP functionality into Claude Desktop
Author: PYNESYS LLC
License: MIT
Project-URL: Homepage, https://github.com/PyneSys/claude_autoapprove_mcp
Project-URL: Repository, https://github.com/PyneSys/claude_autoapprove_mcp
Project-URL: Issues, https://github.com/PyneSys/claude_autoapprove_mcp/issues
Requires-Python: >=3.11
License-File: LICENSE
Requires-Dist: claude-autoapprove==0.2.4
Requires-Dist: fastmcp<3.0.0,>=2.2.0
Requires-Dist: psutil>=7.0.0
Dynamic: license-file
